LICENSE.txt
MANIFEST.in
README.txt
WINDOWS-BUILD.txt
ZopeEdit.spec
make-deb.py
setup.cfg
setup.py
collective/__init__.py
collective.zopeedit.egg-info/PKG-INFO
collective.zopeedit.egg-info/SOURCES.txt
collective.zopeedit.egg-info/dependency_links.txt
collective.zopeedit.egg-info/entry_points.txt
collective.zopeedit.egg-info/namespace_packages.txt
collective.zopeedit.egg-info/not-zip-safe
collective.zopeedit.egg-info/requires.txt
collective.zopeedit.egg-info/top_level.txt
collective/zopeedit/__init__.py
collective/zopeedit/zopeedit.py
collective/zopeedit/Plugins/__init__.py
collective/zopeedit/Plugins/homesite.py
collective/zopeedit/Plugins/homesite5.py
collective/zopeedit/locales/en/LC_MESSAGES/zopeedit.po
collective/zopeedit/locales/es/LC_MESSAGES/zopeedit.po
collective/zopeedit/locales/fr/LC_MESSAGES/zopeedit.po
collective/zopeedit/man/zopeedit.1
collective/zopeedit/posix/collective.zopeedit.pth
collective/zopeedit/posix/preremove.sh
collective/zopeedit/posix/x-zope-edit-zem.xml
collective/zopeedit/posix/zopeedit.desktop
collective/zopeedit/posix/zopeedit.svg
collective/zopeedit/posix/zopeedit_launcher.py
docs/HISTORY.txt
docs/INSTALL-UNIX.txt
docs/INSTALL-WIN32.txt
docs/TODO.txt
docs/USECASES.txt
docs/VERSION.txt