Metadata-Version: 2.1
Name: collective.zopeedit
Version: 1.1.2
Summary: ZopeEdit : External Editor Client
Home-page: https://github.com/collective/collective.zopeedit/
Author: Thierry Benita - atReal
Author-email: contact@atreal.net
License: ZPL
Keywords: zope plone externaleditor zopeedit edition
Platform: UNKNOWN
Classifier: Programming Language :: Python
Classifier: Development Status :: 5 - Production/Stable
Classifier: License :: OSI Approved :: Zope Public License
License-File: LICENSE.txt
